.coveragerc
.gitignore
.travis.yml
CHANGES.rst
CONTRIBUTORS.rst
MANIFEST.in
README.rst
bootstrap.py
buildout.cfg
setup.cfg
setup.py
travis.cfg
versions.cfg
docs/LICENSE.GPL
docs/LICENSE.txt
parts/omelette/collective/themecustomizer/__init__.py
parts/omelette/collective/themecustomizer/config.py
parts/omelette/collective/themecustomizer/configure.zcml
parts/omelette/collective/themecustomizer/controlpanel.py
parts/omelette/collective/themecustomizer/interfaces.py
parts/omelette/collective/themecustomizer/profiles.zcml
parts/omelette/collective/themecustomizer/setuphandlers.py
parts/omelette/collective/themecustomizer/testing.py
parts/omelette/collective/themecustomizer/Extensions/Install.py
parts/omelette/collective/themecustomizer/Extensions/__init__.py
parts/omelette/collective/themecustomizer/browser/__init__.py
parts/omelette/collective/themecustomizer/browser/configure.zcml
parts/omelette/collective/themecustomizer/browser/imagewidget.py
parts/omelette/collective/themecustomizer/browser/viewlets.py
parts/omelette/collective/themecustomizer/browser/templates/header.pt
parts/omelette/collective/themecustomizer/browser/templates/imagewidget.pt
parts/omelette/collective/themecustomizer/browser/templates/logo.pt
parts/omelette/collective/themecustomizer/locales/collective.themecustomizer.pot
parts/omelette/collective/themecustomizer/locales/manual.pot
parts/omelette/collective/themecustomizer/locales/plone.pot
parts/omelette/collective/themecustomizer/locales/es/LC_MESSAGES/collective.themecustomizer.po
parts/omelette/collective/themecustomizer/locales/es/LC_MESSAGES/plone.po
parts/omelette/collective/themecustomizer/locales/pt_BR/LC_MESSAGES/collective.themecustomizer.po
parts/omelette/collective/themecustomizer/locales/pt_BR/LC_MESSAGES/plone.po
parts/omelette/collective/themecustomizer/profiles/default/browserlayer.xml
parts/omelette/collective/themecustomizer/profiles/default/cssregistry.xml
parts/omelette/collective/themecustomizer/profiles/default/metadata.xml
src/collective.themecustomizer.egg-info/PKG-INFO
src/collective.themecustomizer.egg-info/SOURCES.txt
src/collective.themecustomizer.egg-info/dependency_links.txt
src/collective.themecustomizer.egg-info/entry_points.txt
src/collective.themecustomizer.egg-info/namespace_packages.txt
src/collective.themecustomizer.egg-info/not-zip-safe
src/collective.themecustomizer.egg-info/requires.txt
src/collective.themecustomizer.egg-info/top_level.txt
