Metadata-Version: 1.1
Name: collective.themecustomizer
Version: 1.0b1
Summary: Theme customizer for Plone.
Home-page: https://github.com/collective/collective.themecustomizer
Author: Simples Consultoria
Author-email: products@simplesconsultoria.com.br
License: UNKNOWN
Keywords: plone theme customizer
Platform: UNKNOWN
Classifier: Development Status :: 4 - Beta
Classifier: Environment :: Web Environment
Classifier: Framework :: Plone :: 4.2
Classifier: Framework :: Plone :: 4.3
Classifier: Framework :: Plone
Classifier: Intended Audience :: System Administrators
Classifier: License :: OSI Approved :: GNU General Public License v2 (GPLv2)
Classifier: Operating System :: OS Independent
Classifier: Programming Language :: JavaScript
Classifier: Programming Language :: Python :: 2.6
Classifier: Programming Language :: Python :: 2.7
Classifier: Programming Language :: Python
Classifier: Topic :: Software Development :: Libraries :: Python Modules
